rkcu/__init__.py
rkcu/__main__.py
rkcu/config.py
rkcu/enums.py
rkcu/per_key_rgb.py
rkcu/utils.py
rkcu-1.1.0.dist-info/METADATA
rkcu-1.1.0.dist-info/WHEEL
rkcu-1.1.0.dist-info/entry_points.txt
rkcu-1.1.0.dist-info/top_level.txt
rkcu-1.1.0.dist-info/RECORD
