Metadata-Version: 2.4
Name: rkcu
Version: 1.1.0
Summary: Royal Kludge Config Utility - Manage profiles and per-key RGB lighting
Home-page: https://github.com/gagan16k/rkcu
Author: Hardik Srivastava
Maintainer: gagan16k
License: MIT
Project-URL: Homepage, https://github.com/gagan16k/rkcu
Project-URL: Repository, https://github.com/gagan16k/rkcu
Project-URL: Issues, https://github.com/gagan16k/rkcu/issues
Keywords: royal kludge,keyboard,rgb,lighting,config,utility
Classifier: Development Status :: 4 - Beta
Classifier: Intended Audience :: End Users/Desktop
Classifier: License :: OSI Approved :: MIT License
Classifier: Operating System :: OS Independent
Classifier: Programming Language :: Python :: 3
Classifier: Programming Language :: Python :: 3.7
Classifier: Programming Language :: Python :: 3.8
Classifier: Programming Language :: Python :: 3.9
Classifier: Programming Language :: Python :: 3.10
Classifier: Programming Language :: Python :: 3.11
Classifier: Topic :: System :: Hardware
Classifier: Topic :: Utilities
Requires-Python: >=3.7
Requires-Dist: hidapi>=0.10.1
Provides-Extra: dev
Requires-Dist: pytest>=6.0; extra == "dev"
Requires-Dist: black>=21.0.0; extra == "dev"
Requires-Dist: flake8>=3.8.0; extra == "dev"
Dynamic: home-page
Dynamic: requires-python
